mcp_router_use/__init__.py
mcp_router_use/client.py
mcp_router_use/config.py
mcp_router_use/logging.py
mcp_router_use/session.py
mcp_router_use/adapters/__init__.py
mcp_router_use/adapters/base.py
mcp_router_use/adapters/langchain_adapter.py
mcp_router_use/agents/__init__.py
mcp_router_use/agents/base.py
mcp_router_use/agents/mcpagent.py
mcp_router_use/agents/prompts/system_prompt_builder.py
mcp_router_use/agents/prompts/templates.py
mcp_router_use/connectors/__init__.py
mcp_router_use/connectors/base.py
mcp_router_use/connectors/http.py
mcp_router_use/connectors/stdio.py
mcp_router_use/connectors/websocket.py
mcp_router_use/managers/__init__.py
mcp_router_use/managers/server_manager.py
mcp_router_use/managers/tools/__init__.py
mcp_router_use/managers/tools/base_tool.py
mcp_router_use/managers/tools/connect_server.py
mcp_router_use/managers/tools/disconnect_server.py
mcp_router_use/managers/tools/get_active_server.py
mcp_router_use/managers/tools/list_servers_tool.py
mcp_router_use/managers/tools/search_tools.py
mcp_router_use/managers/tools/use_tool.py
mcp_router_use/task_managers/__init__.py
mcp_router_use/task_managers/base.py
mcp_router_use/task_managers/sse.py
mcp_router_use/task_managers/stdio.py
mcp_router_use/task_managers/websocket.py
mcp_router_use-0.1.0.dist-info/METADATA
mcp_router_use-0.1.0.dist-info/WHEEL
mcp_router_use-0.1.0.dist-info/licenses/LICENSE
mcp_router_use-0.1.0.dist-info/RECORD
